{
  "version": "7",
  "dialect": "postgresql",
  "entries": [
    {
      "idx": 0,
      "version": "7",
      "when": 1741993783393,
      "tag": "0000_empty_onslaught",
      "breakpoints": true
    },
    {
      "idx": 1,
      "version": "7",
      "when": 1749573374949,
      "tag": "0001_curved_nicolaos",
      "breakpoints": true
    },
    {
      "idx": 2,
      "version": "7",
      "when": 1749574089182,
      "tag": "0002_previous_senator_kelly",
      "breakpoints": true
    },
    {
      "idx": 3,
      "version": "7",
      "when": 1750184609809,
      "tag": "0003_yummy_stone_men",
      "breakpoints": true
    }
  ]
}